TurkishTopicModel/__init__.py
TurkishTopicModel/PreProcess/Data.py
TurkishTopicModel/PreProcess/Esanlam.py
TurkishTopicModel/PreProcess/ITUNLPTools.py
TurkishTopicModel/PreProcess/Main.py
TurkishTopicModel/PreProcess/Stops.py
TurkishTopicModel/PreProcess/Zemberek.py
TurkishTopicModel/PreProcess/__init__.py
TurkishTopicModel/PreProcess/tests.py
TurkishTopicModel/PreProcess/Config/__init__.py
TurkishTopicModel/PreProcess/Config/dirs.py
TurkishTopicModel/PreProcess/Config/mysql.py
TurkishTopicModel/TopicModel/Main.py
TurkishTopicModel/TopicModel/__init__.py
Turkish_Topic_Model-0.0.2.dist-info/LICENSE
Turkish_Topic_Model-0.0.2.dist-info/METADATA
Turkish_Topic_Model-0.0.2.dist-info/WHEEL
Turkish_Topic_Model-0.0.2.dist-info/top_level.txt
Turkish_Topic_Model-0.0.2.dist-info/RECORD
