Metadata-Version: 2.1
Name: Turkish-Topic-Model
Version: 0.0.2
Summary: Türkçe metin ön işleme ve konu analizi konusunda hazırlanmış fonksiyonlar kümesi
Home-page: UNKNOWN
Author: Ali CIMEN
Author-email: cimenwd@gmail.com
License: UNKNOWN
Platform: UNKNOWN
Classifier: Programming Language :: Python :: 3
Classifier: License :: OSI Approved :: MIT License
Classifier: Operating System :: OS Independent
Requires-Python: >=3.7
License-File: LICENSE
